mcot/core/__init__.py
mcot/core/_write_gifti.py
mcot/core/cifti.py
mcot/core/greyordinate.py
mcot/core/log.py
mcot/core/scripts.py
mcot/core/spherical.py
mcot/core/_scripts/__init__.py
mcot/core/_scripts/__main__.py
mcot/core/_scripts/iter_link.py
mcot/core/_scripts/merge_hcp.py
mcot/core/_scripts/round_bvals.py
mcot/core/_scripts/to_dataframe.py
mcot/core/_scripts/to_dataframe_tree.py
mcot/core/_scripts/cifti/__init__.py
mcot/core/_scripts/cifti/convert.py
mcot/core/_scripts/cifti/correlate.py
mcot/core/_scripts/cifti/ptx2dconn.py
mcot/core/_scripts/cifti/smooth.py
mcot/core/_scripts/function/__init__.py
mcot/core/_scripts/function/__main__.py
mcot/core/_scripts/function/normalize.py
mcot/core/_scripts/gcoord/__init__.py
mcot/core/_scripts/gcoord/__main__.py
mcot/core/_scripts/gcoord/gen.py
mcot/core/_scripts/gcoord/gui.py
mcot/core/_scripts/gcoord/mult.py
mcot/core/_scripts/gcoord/split.py
mcot/core/_scripts/gcoord/transition.py
mcot/core/_scripts/parcel/__init__.py
mcot/core/_scripts/parcel/__main__.py
mcot/core/_scripts/parcel/cluster.py
mcot/core/_scripts/parcel/combine.py
mcot/core/_scripts/parcel/discretise.py
mcot/core/_scripts/parcel/random.py
mcot/core/_scripts/parcel/spectral.py
mcot/core/_scripts/ptx/__init__.py
mcot/core/_scripts/ptx/__main__.py
mcot/core/_scripts/ptx/select_vertex.py
mcot/core/_scripts/split/__init__.py
mcot/core/_scripts/split/__main__.py
mcot/core/_scripts/split/merge.py
mcot/core/_scripts/split/run.py
mcot/core/_scripts/split/submit.py
mcot/core/_scripts/surface/__init__.py
mcot/core/_scripts/surface/__main__.py
mcot/core/_scripts/surface/from_mask.py
mcot/core/_scripts/surface/from_ridge.py
mcot/core/_scripts/surface/gradient.py
mcot/core/_scripts/surface/roi_dist_gifti.py
mcot/core/_scripts/surface/smooth.py
mcot/core/_scripts/surface/watershed.py
mcot/core/_scripts/tree/__init__.py
mcot/core/_scripts/tree/__main__.py
mcot/core/_scripts/tree/extract.py
mcot/core/surface/__init__.py
mcot/core/surface/cortex.py
mcot.core-0.2.5.dist-info/AUTHORS.rst
mcot.core-0.2.5.dist-info/LICENSE
mcot.core-0.2.5.dist-info/METADATA
mcot.core-0.2.5.dist-info/WHEEL
mcot.core-0.2.5.dist-info/entry_points.txt
mcot.core-0.2.5.dist-info/top_level.txt
mcot.core-0.2.5.dist-info/RECORD
