Metadata-Version: 2.1
Name: mcot.core
Version: 0.2.5
Summary: core utilities to work with my code
Home-page: https://git.fmrib.ox.ac.uk/ndcn0236/mcutils
Author: Michiel Cottaar
Author-email: MichielCottaar@pm.me
License: MIT
Platform: UNKNOWN
Classifier: Development Status :: 2 - Pre-Alpha
Classifier: Intended Audience :: Developers
Classifier: License :: OSI Approved :: MIT License
Classifier: Natural Language :: English
Classifier: Programming Language :: Python :: 3 :: Only
Classifier: Programming Language :: Python :: 3.6
Classifier: Programming Language :: Python :: 3.7
Classifier: Programming Language :: Python :: 3.8
Requires-Dist: numpy
Requires-Dist: scipy
Requires-Dist: nibabel
Requires-Dist: numba
Requires-Dist: six
Requires-Dist: loguru
Requires-Dist: fslpy
Requires-Dist: zarr
Requires-Dist: h5py
Requires-Dist: colorcet
Requires-Dist: dask[array]
Requires-Dist: pandas
Requires-Dist: sklearn
Requires-Dist: scikit-image
